detectree/__init__.py
detectree/classifier.py
detectree/filters.py
detectree/image_descriptor.py
detectree/lidar.py
detectree/pixel_features.py
detectree/pixel_response.py
detectree/settings.py
detectree/train_test_split.py
detectree/utils.py
detectree/cli/__init__.py
detectree/cli/main.py
detectree-0.8.1.dist-info/licenses/LICENSE
detectree-0.8.1.dist-info/METADATA
detectree-0.8.1.dist-info/WHEEL
detectree-0.8.1.dist-info/entry_points.txt
detectree-0.8.1.dist-info/top_level.txt
detectree-0.8.1.dist-info/RECORD
