Metadata-Version: 2.4
Name: detectree
Version: 0.8.1
Summary: Tree detection from aerial imagery in Python.
Author-email: Martí Bosch <marti.bosch@epfl.ch>
License: GPL-3.0
Project-URL: Repository, https://github.com/martibosch/detectree
Classifier: License :: OSI Approved :: GNU General Public License v3 (GPLv3)
Classifier: Natural Language :: English
Classifier: Programming Language :: Python :: 3
Classifier: Programming Language :: Python :: 3.10
Classifier: Programming Language :: Python :: 3.11
Classifier: Programming Language :: Python :: 3.12
Classifier: Programming Language :: Python :: 3.13
Requires-Python: >=3.10
License-File: LICENSE
Requires-Dist: dask[delayed,distributed]
Requires-Dist: huggingface-hub
Requires-Dist: joblib
Requires-Dist: laspy[lazrs]>=2.0.0
Requires-Dist: lightgbm
Requires-Dist: numpy>=1.15
Requires-Dist: opencv-python>=4.0.0
Requires-Dist: pandas>=0.23
Requires-Dist: pymaxflow>=1.0.0
Requires-Dist: rasterio>=1.0.0
Requires-Dist: scikit-image>=0.25.0
Requires-Dist: scikit-learn
Requires-Dist: scipy>=1.0.0
Requires-Dist: skops
Requires-Dist: shapely
Requires-Dist: tqdm
Provides-Extra: test
Requires-Dist: coverage[toml]; extra == "test"
Requires-Dist: pytest; extra == "test"
Requires-Dist: pytest-cov; extra == "test"
Requires-Dist: ruff; extra == "test"
Provides-Extra: dev
Requires-Dist: build; extra == "dev"
Requires-Dist: commitizen; extra == "dev"
Requires-Dist: pre-commit; extra == "dev"
Requires-Dist: pip; extra == "dev"
Requires-Dist: toml; extra == "dev"
Requires-Dist: tox; extra == "dev"
Requires-Dist: twine; extra == "dev"
Provides-Extra: doc
Requires-Dist: pydata-sphinx-theme; extra == "doc"
Requires-Dist: sphinx; extra == "doc"
Requires-Dist: sphinx-click; extra == "doc"
Requires-Dist: sphinx-mdinclude; extra == "doc"
Requires-Dist: sphinxcontrib-bibtex; extra == "doc"
Dynamic: license-file
